{"data":[{"pref_labels":[{"label":"Fritter apple","language":"en"}],"uri":"http://www.foodvoc.org/resource/nevo#foodItem2869"},{"pref_labels":[{"label":"Buttermilk curds fresh","language":"en"}],"uri":"http://www.foodvoc.org/resource/nevo#foodItem287"},{"pref_labels":[{"label":"Candybar Lion","language":"en"}],"uri":"http://www.foodvoc.org/resource/nevo#foodItem2870"},{"pref_labels":[{"label":"Sauce caramel for pudding","language":"en"}],"uri":"http://www.foodvoc.org/resource/nevo#foodItem2873"},{"pref_labels":[{"label":"Fruit snack Knijpfruit/Slurpfruit","language":"en"}],"uri":"http://www.foodvoc.org/resource/nevo#foodItem2875"},{"pref_labels":[{"label":"Bread brioche","language":"en"}],"uri":"http://www.foodvoc.org/resource/nevo#foodItem2876"},{"pref_labels":[{"label":"Low fat margarine product Gezonde Start 35-40% fat <10g sat salted","language":"en"}],"uri":"http://www.foodvoc.org/resource/nevo#foodItem2878"},{"pref_labels":[{"label":"Porridge oatmeal prepared w whole milk unsweetened","language":"en"}],"uri":"http://www.foodvoc.org/resource/nevo#foodItem288"},{"pref_labels":[{"label":"Coffee wiener melange instant powder","language":"en"}],"uri":"http://www.foodvoc.org/resource/nevo#foodItem2880"},{"pref_labels":[{"label":"Coffee wiener melange instant prepared","language":"en"}],"uri":"http://www.foodvoc.org/resource/nevo#foodItem2881"},{"pref_labels":[{"label":"Beef smoke-dried lightly salted","language":"en"}],"uri":"http://www.foodvoc.org/resource/nevo#foodItem2883"},{"pref_labels":[{"label":"Sugar demarara","language":"en"}],"uri":"http://www.foodvoc.org/resource/nevo#foodItem2884"},{"pref_labels":[{"label":"Cranberry compote sweetened","language":"en"}],"uri":"http://www.foodvoc.org/resource/nevo#foodItem2885"},{"pref_labels":[{"label":"Cashew nuts salted","language":"en"}],"uri":"http://www.foodvoc.org/resource/nevo#foodItem2886"},{"pref_labels":[{"label":"Almonds blanched salted","language":"en"}],"uri":"http://www.foodvoc.org/resource/nevo#foodItem2887"},{"pref_labels":[{"label":"Soya based yogurt plain Alpro","language":"en"}],"uri":"http://www.foodvoc.org/resource/nevo#foodItem2888"},{"pref_labels":[{"label":"Buttermilk","language":"en"}],"uri":"http://www.foodvoc.org/resource/nevo#foodItem289"},{"pref_labels":[{"label":"Cranberries dried sweetened","language":"en"}],"uri":"http://www.foodvoc.org/resource/nevo#foodItem2890"},{"pref_labels":[{"label":"Biscuit Dutch Jodekoek","language":"en"}],"uri":"http://www.foodvoc.org/resource/nevo#foodItem2891"},{"pref_labels":[{"label":"Waffle penny-","language":"en"}],"uri":"http://www.foodvoc.org/resource/nevo#foodItem2892"},{"pref_labels":[{"label":"Cake Indonesian","language":"en"}],"uri":"http://www.foodvoc.org/resource/nevo#foodItem2893"},{"pref_labels":[{"label":"Biscuit digestive","language":"en"}],"uri":"http://www.foodvoc.org/resource/nevo#foodItem2894"},{"pref_labels":[{"label":"Low fat spread AH omega-3","language":"en"}],"uri":"http://www.foodvoc.org/resource/nevo#foodItem2895"},{"pref_labels":[{"label":"Juice Drink Ocean Spray","language":"en"}],"uri":"http://www.foodvoc.org/resource/nevo#foodItem2897"},{"pref_labels":[{"label":"Horse meat smoked","language":"en"}],"uri":"http://www.foodvoc.org/resource/nevo#foodItem2898"},{"pref_labels":[{"label":"Scrapple, pork","language":"en"}],"uri":"http://www.foodvoc.org/resource/nevo#foodItem2899"},{"pref_labels":[{"label":"Swede boiled","language":"en"}],"uri":"http://www.foodvoc.org/resource/nevo#foodItem29"},{"pref_labels":[{"label":"Porridge buttermilk w wheat flour white","language":"en"}],"uri":"http://www.foodvoc.org/resource/nevo#foodItem290"},{"pref_labels":[{"label":"Sweetcorn tinned","language":"en"}],"uri":"http://www.foodvoc.org/resource/nevo#foodItem2900"},{"pref_labels":[{"label":"Sausage beef Braadworst prepared","language":"en"}],"uri":"http://www.foodvoc.org/resource/nevo#foodItem2901"},{"pref_labels":[{"label":"Beef breast boneless prepared","language":"en"}],"uri":"http://www.foodvoc.org/resource/nevo#foodItem2902"},{"pref_labels":[{"label":"Beef olives prepared","language":"en"}],"uri":"http://www.foodvoc.org/resource/nevo#foodItem2903"},{"pref_labels":[{"label":"Beef T-bone steak prepared","language":"en"}],"uri":"http://www.foodvoc.org/resource/nevo#foodItem2904"},{"pref_labels":[{"label":"Beef ribeye steak prepared","language":"en"}],"uri":"http://www.foodvoc.org/resource/nevo#foodItem2905"},{"pref_labels":[{"label":"Pork shoarma seasoning prepared","language":"en"}],"uri":"http://www.foodvoc.org/resource/nevo#foodItem2906"},{"pref_labels":[{"label":"Bacon lean smoked prepared","language":"en"}],"uri":"http://www.foodvoc.org/resource/nevo#foodItem2907"},{"pref_labels":[{"label":"Pork sparerib prepared","language":"en"}],"uri":"http://www.foodvoc.org/resource/nevo#foodItem2908"},{"pref_labels":[{"label":"Pork stewing meat prepared","language":"en"}],"uri":"http://www.foodvoc.org/resource/nevo#foodItem2909"},{"pref_labels":[{"label":"Topping dessert powder w sugar Klop-Klop","language":"en"}],"uri":"http://www.foodvoc.org/resource/nevo#foodItem291"},{"pref_labels":[{"label":"Veal stewing meat prepared","language":"en"}],"uri":"http://www.foodvoc.org/resource/nevo#foodItem2910"},{"pref_labels":[{"label":"Veal stewing steak prepared","language":"en"}],"uri":"http://www.foodvoc.org/resource/nevo#foodItem2911"},{"pref_labels":[{"label":"Sausage veal Braadworst prepared","language":"en"}],"uri":"http://www.foodvoc.org/resource/nevo#foodItem2912"},{"pref_labels":[{"label":"Veal rib steak prepared","language":"en"}],"uri":"http://www.foodvoc.org/resource/nevo#foodItem2913"},{"pref_labels":[{"label":"Veal frying steak prepared","language":"en"}],"uri":"http://www.foodvoc.org/resource/nevo#foodItem2914"},{"pref_labels":[{"label":"Veal tenderloin medaillon prepared","language":"en"}],"uri":"http://www.foodvoc.org/resource/nevo#foodItem2915"},{"pref_labels":[{"label":"Cracker VitaLU w added calcium","language":"en"}],"uri":"http://www.foodvoc.org/resource/nevo#foodItem2916"},{"pref_labels":[{"label":"Coffee creamer low fat","language":"en"}],"uri":"http://www.foodvoc.org/resource/nevo#foodItem292"},{"pref_labels":[{"label":"Yoghurt drink Fristi","language":"en"}],"uri":"http://www.foodvoc.org/resource/nevo#foodItem2921"},{"pref_labels":[{"label":"Potatoes waxy average wo skin boiled","language":"en"}],"uri":"http://www.foodvoc.org/resource/nevo#foodItem2922"},{"pref_labels":[{"label":"Crisps potato unflavoured","language":"en"}],"uri":"http://www.foodvoc.org/resource/nevo#foodItem2923"},{"pref_labels":[{"label":"Crisps potato flavoured","language":"en"}],"uri":"http://www.foodvoc.org/resource/nevo#foodItem2924"},{"pref_labels":[{"label":"Mascarpone cheese","language":"en"}],"uri":"http://www.foodvoc.org/resource/nevo#foodItem2925"},{"pref_labels":[{"label":"Crisps potato light flavoured","language":"en"}],"uri":"http://www.foodvoc.org/resource/nevo#foodItem2926"},{"pref_labels":[{"label":"Crisps potato straws natural","language":"en"}],"uri":"http://www.foodvoc.org/resource/nevo#foodItem2927"},{"pref_labels":[{"label":"Crisps potato straws flavoured","language":"en"}],"uri":"http://www.foodvoc.org/resource/nevo#foodItem2928"},{"pref_labels":[{"label":"Crisps potato Lays Sensations flavoured","language":"en"}],"uri":"http://www.foodvoc.org/resource/nevo#foodItem2929"},{"pref_labels":[{"label":"Coffee creamer","language":"en"}],"uri":"http://www.foodvoc.org/resource/nevo#foodItem293"},{"pref_labels":[{"label":"Chocolate spread white","language":"en"}],"uri":"http://www.foodvoc.org/resource/nevo#foodItem2930"},{"pref_labels":[{"label":"Bread multigrain wholemeal Becel","language":"en"}],"uri":"http://www.foodvoc.org/resource/nevo#foodItem2931"},{"pref_labels":[{"label":"Soup portion prepared","language":"en"}],"uri":"http://www.foodvoc.org/resource/nevo#foodItem2932"},{"pref_labels":[{"label":"Sponge cake wholemeal/multigrain","language":"en"}],"uri":"http://www.foodvoc.org/resource/nevo#foodItem2933"},{"pref_labels":[{"label":"Low fat spead Becel pro-activ calorie light","language":"en"}],"uri":"http://www.foodvoc.org/resource/nevo#foodItem2934"},{"pref_labels":[{"label":"Yogurt full fat plain Activia","language":"en"}],"uri":"http://www.foodvoc.org/resource/nevo#foodItem2935"},{"pref_labels":[{"label":"Yoghurt drink Activia Start","language":"en"}],"uri":"http://www.foodvoc.org/resource/nevo#foodItem2936"},{"pref_labels":[{"label":"Toast Melba natural","language":"en"}],"uri":"http://www.foodvoc.org/resource/nevo#foodItem2937"},{"pref_labels":[{"label":"Toast Melba other varieties","language":"en"}],"uri":"http://www.foodvoc.org/resource/nevo#foodItem2938"},{"pref_labels":[{"label":"Icecream based on coconutmilk","language":"en"}],"uri":"http://www.foodvoc.org/resource/nevo#foodItem2939"},{"pref_labels":[{"label":"Milk skimmed","language":"en"}],"uri":"http://www.foodvoc.org/resource/nevo#foodItem294"},{"pref_labels":[{"label":"Pizza w cheese and vegetables frozen unprepared","language":"en"}],"uri":"http://www.foodvoc.org/resource/nevo#foodItem2942"},{"pref_labels":[{"label":"Pizza w meat frozen unprepared","language":"en"}],"uri":"http://www.foodvoc.org/resource/nevo#foodItem2943"},{"pref_labels":[{"label":"Pizza w fish frozen unprepared","language":"en"}],"uri":"http://www.foodvoc.org/resource/nevo#foodItem2944"},{"pref_labels":[{"label":"Pizza salami frozen unprepared","language":"en"}],"uri":"http://www.foodvoc.org/resource/nevo#foodItem2945"},{"pref_labels":[{"label":"Pizza w ham and pineapple frozen unprep","language":"en"}],"uri":"http://www.foodvoc.org/resource/nevo#foodItem2946"},{"pref_labels":[{"label":"Herring pickled w gherkin","language":"en"}],"uri":"http://www.foodvoc.org/resource/nevo#foodItem2947"},{"pref_labels":[{"label":"Salad egg w potato","language":"en"}],"uri":"http://www.foodvoc.org/resource/nevo#foodItem2948"},{"pref_labels":[{"label":"Salad salmon w potato","language":"en"}],"uri":"http://www.foodvoc.org/resource/nevo#foodItem2949"},{"pref_labels":[{"label":"Milk skimmed dried","language":"en"}],"uri":"http://www.foodvoc.org/resource/nevo#foodItem295"},{"pref_labels":[{"label":"Salad meat w potato","language":"en"}],"uri":"http://www.foodvoc.org/resource/nevo#foodItem2950"},{"pref_labels":[{"label":"Nuggets vegetarian unprepared","language":"en"}],"uri":"http://www.foodvoc.org/resource/nevo#foodItem2951"},{"pref_labels":[{"label":"Biscuit spiced small Kruidnoten w chocolate average","language":"en"}],"uri":"http://www.foodvoc.org/resource/nevo#foodItem2952"},{"pref_labels":[{"label":"Salt sea","language":"en"}],"uri":"http://www.foodvoc.org/resource/nevo#foodItem2953"},{"pref_labels":[{"label":"Apple dried soaked in water","language":"en"}],"uri":"http://www.foodvoc.org/resource/nevo#foodItem2954"},{"pref_labels":[{"label":"Pear dried soaked in water","language":"en"}],"uri":"http://www.foodvoc.org/resource/nevo#foodItem2955"},{"pref_labels":[{"label":"Prunes soaked in water","language":"en"}],"uri":"http://www.foodvoc.org/resource/nevo#foodItem2956"},{"pref_labels":[{"label":"Fruit mixed dried soaked in water","language":"en"}],"uri":"http://www.foodvoc.org/resource/nevo#foodItem2957"},{"pref_labels":[{"label":"Milk whole dried","language":"en"}],"uri":"http://www.foodvoc.org/resource/nevo#foodItem296"},{"pref_labels":[{"label":"Milk human","language":"en"}],"uri":"http://www.foodvoc.org/resource/nevo#foodItem297"},{"pref_labels":[{"label":"Porridge rice","language":"en"}],"uri":"http://www.foodvoc.org/resource/nevo#foodItem298"},{"pref_labels":[{"label":"Toddler formula Nutrilon 4 p 100 ml","language":"en"}],"uri":"http://www.foodvoc.org/resource/nevo#foodItem2983"},{"pref_labels":[{"label":"Toddler formula Nutrilon 5 p 100 ml","language":"en"}],"uri":"http://www.foodvoc.org/resource/nevo#foodItem2984"},{"pref_labels":[{"label":"Cream whipping unprepared","language":"en"}],"uri":"http://www.foodvoc.org/resource/nevo#foodItem299"},{"pref_labels":[{"label":"Falafel unprepared","language":"en"}],"uri":"http://www.foodvoc.org/resource/nevo#foodItem2994"},{"pref_labels":[{"label":"Cheese spread 45+","language":"en"}],"uri":"http://www.foodvoc.org/resource/nevo#foodItem2995"},{"pref_labels":[{"label":"Sausage Chorizo","language":"en"}],"uri":"http://www.foodvoc.org/resource/nevo#foodItem2996"},{"pref_labels":[{"label":"Sausage grill","language":"en"}],"uri":"http://www.foodvoc.org/resource/nevo#foodItem2997"},{"pref_labels":[{"label":"Potatoes old raw","language":"en"}],"uri":"http://www.foodvoc.org/resource/nevo#foodItem3"},{"pref_labels":[{"label":"Kohlrabi boiled","language":"en"}],"uri":"http://www.foodvoc.org/resource/nevo#foodItem30"},{"pref_labels":[{"label":"Yoghurt Bulgarian whole milk","language":"en"}],"uri":"http://www.foodvoc.org/resource/nevo#foodItem300"},{"pref_labels":[{"label":"Turkey (processed meat product)","language":"en"}],"uri":"http://www.foodvoc.org/resource/nevo#foodItem3001"},{"pref_labels":[{"label":"Bacon smoked Katenspek","language":"en"}],"uri":"http://www.foodvoc.org/resource/nevo#foodItem3002"},{"pref_labels":[{"label":"Sausage beef frankfurter type tinned","language":"en"}],"uri":"http://www.foodvoc.org/resource/nevo#foodItem3003"},{"pref_labels":[{"label":"Milk chocolate-flavoured w sw Optimel","language":"en"}],"uri":"http://www.foodvoc.org/resource/nevo#foodItem3004"},{"pref_labels":[{"label":"Bread low in carbohydrates","language":"en"}],"uri":"http://www.foodvoc.org/resource/nevo#foodItem3007"},{"pref_labels":[{"label":"Shandy","language":"en"}],"uri":"http://www.foodvoc.org/resource/nevo#foodItem3009"},{"pref_labels":[{"label":"Yoghurt low fat","language":"en"}],"uri":"http://www.foodvoc.org/resource/nevo#foodItem301"},{"pref_labels":[{"label":"Veal schnitzel not breaded raw","language":"en"}],"uri":"http://www.foodvoc.org/resource/nevo#foodItem3016"},{"pref_labels":[{"label":"Minced veal raw","language":"en"}],"uri":"http://www.foodvoc.org/resource/nevo#foodItem3017"},{"pref_labels":[{"label":"Veal tenderloin medaillon raw","language":"en"}],"uri":"http://www.foodvoc.org/resource/nevo#foodItem3018"},{"pref_labels":[{"label":"Veal frying steak raw","language":"en"}],"uri":"http://www.foodvoc.org/resource/nevo#foodItem3019"},{"pref_labels":[{"label":"Veal rib steak raw","language":"en"}],"uri":"http://www.foodvoc.org/resource/nevo#foodItem3020"},{"pref_labels":[{"label":"Sausage veal Braadworst raw","language":"en"}],"uri":"http://www.foodvoc.org/resource/nevo#foodItem3021"},{"pref_labels":[{"label":"Veal stewing steak raw","language":"en"}],"uri":"http://www.foodvoc.org/resource/nevo#foodItem3022"},{"pref_labels":[{"label":"Veal stewing meat raw","language":"en"}],"uri":"http://www.foodvoc.org/resource/nevo#foodItem3023"},{"pref_labels":[{"label":"Pork stewing meat raw","language":"en"}],"uri":"http://www.foodvoc.org/resource/nevo#foodItem3024"},{"pref_labels":[{"label":"Bacon lean smoked raw","language":"en"}],"uri":"http://www.foodvoc.org/resource/nevo#foodItem3025"},{"pref_labels":[{"label":"Bacon rasher prepared in own fat","language":"en"}],"uri":"http://www.foodvoc.org/resource/nevo#foodItem3026"},{"pref_labels":[{"label":"Pork shoarma seasoning raw","language":"en"}],"uri":"http://www.foodvoc.org/resource/nevo#foodItem3027"},{"pref_labels":[{"label":"Beef breast boneless raw","language":"en"}],"uri":"http://www.foodvoc.org/resource/nevo#foodItem3028"},{"pref_labels":[{"label":"Minced veal shallow fried","language":"en"}],"uri":"http://www.foodvoc.org/resource/nevo#foodItem3029"},{"pref_labels":[{"label":"Ice cream dairy","language":"en"}],"uri":"http://www.foodvoc.org/resource/nevo#foodItem303"},{"pref_labels":[{"label":"Sausage beef Braadworst raw","language":"en"}],"uri":"http://www.foodvoc.org/resource/nevo#foodItem3030"},{"pref_labels":[{"label":"Pork sparerib raw","language":"en"}],"uri":"http://www.foodvoc.org/resource/nevo#foodItem3031"},{"pref_labels":[{"label":"Beef ribeye steak raw","language":"en"}],"uri":"http://www.foodvoc.org/resource/nevo#foodItem3032"},{"pref_labels":[{"label":"Beef T-bone steak raw","language":"en"}],"uri":"http://www.foodvoc.org/resource/nevo#foodItem3033"},{"pref_labels":[{"label":"Minced beef lean raw","language":"en"}],"uri":"http://www.foodvoc.org/resource/nevo#foodItem3034"},{"pref_labels":[{"label":"Minced beef lean shallow fried","language":"en"}],"uri":"http://www.foodvoc.org/resource/nevo#foodItem3035"},{"pref_labels":[{"label":"Gravy 75% fat thickend prep w gravy instant powder","language":"en"}],"uri":"http://www.foodvoc.org/resource/nevo#foodItem3036"},{"pref_labels":[{"label":"Gravy 75% fat clear prep w gravy instant powder","language":"en"}],"uri":"http://www.foodvoc.org/resource/nevo#foodItem3037"},{"pref_labels":[{"label":"Gravy 5% fat clear prep w gravy instant powder","language":"en"}],"uri":"http://www.foodvoc.org/resource/nevo#foodItem3038"},{"pref_labels":[{"label":"Veal schnitzel not breaded prepared","language":"en"}],"uri":"http://www.foodvoc.org/resource/nevo#foodItem3039"},{"pref_labels":[{"label":"Cheese Swiss dried","language":"en"}],"uri":"http://www.foodvoc.org/resource/nevo#foodItem304"},{"pref_labels":[{"label":"Vegetarian prod filled w cheese Valess unprep","language":"en"}],"uri":"http://www.foodvoc.org/resource/nevo#foodItem3040"},{"pref_labels":[{"label":"Vegetarian product filled filet Valess unprep","language":"en"}],"uri":"http://www.foodvoc.org/resource/nevo#foodItem3041"},{"pref_labels":[{"label":"Pizza Turkish without extras","language":"en"}],"uri":"http://www.foodvoc.org/resource/nevo#foodItem3042"},{"pref_labels":[{"label":"Yoghurt Turkish 4% fat","language":"en"}],"uri":"http://www.foodvoc.org/resource/nevo#foodItem3043"},{"pref_labels":[{"label":"Cheese Turkish 60+ cow's milk canned","language":"en"}],"uri":"http://www.foodvoc.org/resource/nevo#foodItem3044"},{"pref_labels":[{"label":"Cheese sheep/goat Turkish 50+ canned","language":"en"}],"uri":"http://www.foodvoc.org/resource/nevo#foodItem3045"},{"pref_labels":[{"label":"Bread brown Turkish","language":"en"}],"uri":"http://www.foodvoc.org/resource/nevo#foodItem3046"},{"pref_labels":[{"label":"Yoghurt Turkish 10% fat","language":"en"}],"uri":"http://www.foodvoc.org/resource/nevo#foodItem3047"},{"pref_labels":[{"label":"Sweet pepper orange raw","language":"en"}],"uri":"http://www.foodvoc.org/resource/nevo#foodItem3048"},{"pref_labels":[{"label":"Beans white canned","language":"en"}],"uri":"http://www.foodvoc.org/resource/nevo#foodItem3049"},{"pref_labels":[{"label":"Quark low fat","language":"en"}],"uri":"http://www.foodvoc.org/resource/nevo#foodItem305"},{"pref_labels":[{"label":"Porridge oatmeal prepared w semi-skimmed milk unsweetened","language":"en"}],"uri":"http://www.foodvoc.org/resource/nevo#foodItem3050"},{"pref_labels":[{"label":"Oil linseed","language":"en"}],"uri":"http://www.foodvoc.org/resource/nevo#foodItem3051"},{"pref_labels":[{"label":"Butter product melange unsalted Campina Botergoud","language":"en"}],"uri":"http://www.foodvoc.org/resource/nevo#foodItem3052"},{"pref_labels":[{"label":"Bread brown wheat low sodium","language":"en"}],"uri":"http://www.foodvoc.org/resource/nevo#foodItem3056"},{"pref_labels":[{"label":"Oat bran","language":"en"}],"uri":"http://www.foodvoc.org/resource/nevo#foodItem3058"},{"pref_labels":[{"label":"Muesli crunchy Cruesli Balans","language":"en"}],"uri":"http://www.foodvoc.org/resource/nevo#foodItem3059"},{"pref_labels":[{"label":"Quark half fat","language":"en"}],"uri":"http://www.foodvoc.org/resource/nevo#foodItem306"},{"pref_labels":[{"label":"Apple turnover w puff pastry w butter","language":"en"}],"uri":"http://www.foodvoc.org/resource/nevo#foodItem3060"},{"pref_labels":[{"label":"Syrup maple","language":"en"}],"uri":"http://www.foodvoc.org/resource/nevo#foodItem3063"},{"pref_labels":[{"label":"Syrup apple enriched w iron","language":"en"}],"uri":"http://www.foodvoc.org/resource/nevo#foodItem3064"},{"pref_labels":[{"label":"Cream whipped low fat w sweetener canned","language":"en"}],"uri":"http://www.foodvoc.org/resource/nevo#foodItem3065"},{"pref_labels":[{"label":"Cream whipped low fat w sugar canned","language":"en"}],"uri":"http://www.foodvoc.org/resource/nevo#foodItem3066"},{"pref_labels":[{"label":"Sweets cream hard","language":"en"}],"uri":"http://www.foodvoc.org/resource/nevo#foodItem3067"},{"pref_labels":[{"label":"Fruit drink concentrated Vruchtenmix","language":"en"}],"uri":"http://www.foodvoc.org/resource/nevo#foodItem3068"},{"pref_labels":[{"label":"Vegetables for soup cooked","language":"en"}],"uri":"http://www.foodvoc.org/resource/nevo#foodItem3069"},{"pref_labels":[{"label":"Quark full fat","language":"en"}],"uri":"http://www.foodvoc.org/resource/nevo#foodItem307"},{"pref_labels":[{"label":"Tuna prepared without fat","language":"en"}],"uri":"http://www.foodvoc.org/resource/nevo#foodItem3070"},{"pref_labels":[{"label":"Tilapia prepared without fat","language":"en"}],"uri":"http://www.foodvoc.org/resource/nevo#foodItem3071"},{"pref_labels":[{"label":"Deep fried legumes Bara Surinam","language":"en"}],"uri":"http://www.foodvoc.org/resource/nevo#foodItem3072"},{"pref_labels":[{"label":"Beans mung boiled","language":"en"}],"uri":"http://www.foodvoc.org/resource/nevo#foodItem3073"},{"pref_labels":[{"label":"Yoghurt full fat w fruit/vanilla Activia","language":"en"}],"uri":"http://www.foodvoc.org/resource/nevo#foodItem3074"},{"pref_labels":[{"label":"Pastry puff cheese filled deep-fried in liquid fat","language":"en"}],"uri":"http://www.foodvoc.org/resource/nevo#foodItem3075"},{"pref_labels":[{"label":"Puff pastry w butter baked","language":"en"}],"uri":"http://www.foodvoc.org/resource/nevo#foodItem3076"},{"pref_labels":[{"label":"Bread white gluten free Pan Carre Schar","language":"en"}],"uri":"http://www.foodvoc.org/resource/nevo#foodItem3077"},{"pref_labels":[{"label":"Bread multigrain gluten free Rustico Schar","language":"en"}],"uri":"http://www.foodvoc.org/resource/nevo#foodItem3078"},{"pref_labels":[{"label":"Bread sourdough gluten free Pain Campagnard Schar","language":"en"}],"uri":"http://www.foodvoc.org/resource/nevo#foodItem3079"},{"pref_labels":[{"label":"Oil peanut","language":"en"}],"uri":"http://www.foodvoc.org/resource/nevo#foodItem308"},{"pref_labels":[{"label":"Crispbread gluten free Fette Croccanti Schar","language":"en"}],"uri":"http://www.foodvoc.org/resource/nevo#foodItem3080"},{"pref_labels":[{"label":"Baking mix white gluten free Schar","language":"en"}],"uri":"http://www.foodvoc.org/resource/nevo#foodItem3081"},{"pref_labels":[{"label":"Baking mix brown gluten free Schar","language":"en"}],"uri":"http://www.foodvoc.org/resource/nevo#foodItem3082"},{"pref_labels":[{"label":"Processed meat prod 10-20 g fat ex liver average","language":"en"}],"uri":"http://www.foodvoc.org/resource/nevo#foodItem3084"},{"pref_labels":[{"label":"Mustard leaves boiled","language":"en"}],"uri":"http://www.foodvoc.org/resource/nevo#foodItem3085"},{"pref_labels":[{"label":"Cabbage pak-choi cooked","language":"en"}],"uri":"http://www.foodvoc.org/resource/nevo#foodItem3086"},{"pref_labels":[{"label":"Sweet pepper green raw","language":"en"}],"uri":"http://www.foodvoc.org/resource/nevo#foodItem31"},{"pref_labels":[{"label":"Butter unsalted","language":"en"}],"uri":"http://www.foodvoc.org/resource/nevo#foodItem310"},{"pref_labels":[{"label":"Toddler formula Hero Baby 4 p 100 ml","language":"en"}],"uri":"http://www.foodvoc.org/resource/nevo#foodItem3115"},{"pref_labels":[{"label":"Toddler formula Hero Baby 5 p 100 ml","language":"en"}],"uri":"http://www.foodvoc.org/resource/nevo#foodItem3117"},{"pref_labels":[{"label":"Parsnip raw","language":"en"}],"uri":"http://www.foodvoc.org/resource/nevo#foodItem3127"},{"pref_labels":[{"label":"Parsnip boiled","language":"en"}],"uri":"http://www.foodvoc.org/resource/nevo#foodItem3128"},{"pref_labels":[{"label":"Toddler formula Nestle groeimelk 1+ p 100 ml","language":"en"}],"uri":"http://www.foodvoc.org/resource/nevo#foodItem3129"},{"pref_labels":[{"label":"Oil soy","language":"en"}],"uri":"http://www.foodvoc.org/resource/nevo#foodItem313"},{"pref_labels":[{"label":"Toddler formula Nestle groeimelk 2+ p 100 ml","language":"en"}],"uri":"http://www.foodvoc.org/resource/nevo#foodItem3130"},{"pref_labels":[{"label":"Breakfast cereal porridge Nestle Pyjamapapje fijne tarwe granen","language":"en"}],"uri":"http://www.foodvoc.org/resource/nevo#foodItem3131"},{"pref_labels":[{"label":"Breakfast cereal porridge Nestle Pyjamapapje 8 granen","language":"en"}],"uri":"http://www.foodvoc.org/resource/nevo#foodItem3132"},{"pref_labels":[{"label":"Flour rice with vanilla Nestle Pyjamapapje","language":"en"}],"uri":"http://www.foodvoc.org/resource/nevo#foodItem3133"},{"pref_labels":[{"label":"Bitter gourd pods boiled","language":"en"}],"uri":"http://www.foodvoc.org/resource/nevo#foodItem3134"},{"pref_labels":[{"label":"Okra boiled","language":"en"}],"uri":"http://www.foodvoc.org/resource/nevo#foodItem3135"},{"pref_labels":[{"label":"Cod dried, salted, soaked, boiled","language":"en"}],"uri":"http://www.foodvoc.org/resource/nevo#foodItem3137"},{"pref_labels":[{"label":"Sauce soy","language":"en"}],"uri":"http://www.foodvoc.org/resource/nevo#foodItem3138"},{"pref_labels":[{"label":"Mince chicken raw","language":"en"}],"uri":"http://www.foodvoc.org/resource/nevo#foodItem3139"},{"pref_labels":[{"label":"Lard","language":"en"}],"uri":"http://www.foodvoc.org/resource/nevo#foodItem314"},{"pref_labels":[{"label":"Beef fat","language":"en"}],"uri":"http://www.foodvoc.org/resource/nevo#foodItem315"},{"pref_labels":[{"label":"Margarine product 60% fat >17 g sat salted","language":"en"}],"uri":"http://www.foodvoc.org/resource/nevo#foodItem3152"},{"pref_labels":[{"label":"Quinoa raw","language":"en"}],"uri":"http://www.foodvoc.org/resource/nevo#foodItem3153"},{"pref_labels":[{"label":"Quinoa cooked","language":"en"}],"uri":"http://www.foodvoc.org/resource/nevo#foodItem3154"},{"pref_labels":[{"label":"Cheese 30+ age 4-8 weeks","language":"en"}],"uri":"http://www.foodvoc.org/resource/nevo#foodItem3155"},{"pref_labels":[{"label":"Infant formula Kruidvat Standaard 1 p 100 ml","language":"en"}],"uri":"http://www.foodvoc.org/resource/nevo#foodItem3156"},{"pref_labels":[{"label":"Toddler formula Kruidvat Standaard 2 p 100 ml","language":"en"}],"uri":"http://www.foodvoc.org/resource/nevo#foodItem3157"}],"success":"Resource created."}
